[
    {
        "name": "Увод у информационе системе",
        "lecture_session_time": "Понедељак - 08:15-10:00 Амфитеатар 1 (А7,А8,А9,А10)"
    },
    {
        "name": "Принципи програмирања",
        "lecture_session_time": "Понедељак - 08:15-10:00 Амфитеатар 5 (А1,А2,А3)"
    },
    {
        "name": "Математика 2",
        "lecture_session_time": "Понедељак - 08:15-10:00 Амфитеатар 4 (А4,А5,А6)"
    },
    {
        "name": "Принципи програмирања",
        "lecture_session_time": "Понедељак - 10:15-12:00 Амфитеатар 2 (А7,А8,А9,А10)"
    },
    {
        "name": "Увод у информационе системе",
        "lecture_session_time": "Понедељак - 10:15-12:00 Амфитеатар 4 (А4,А5,А6)"
    },
    {
        "name": "Математика 2",
        "lecture_session_time": "Понедељак - 10:15-12:00 Амфитеатар 5 (А1,А2,А3)"
    },
    {
        "name": "Основе операционог менаџмента",
        "lecture_session_time": "Понедељак - 12:15-14:00 20 (А1,А2,А3,А4,А5,А6,А7,А8,А9,А10)"
    },
    {
        "name": "Психологија",
        "lecture_session_time": "Понедељак - 12:15-14:00 Амфитеатар 1 (А11,А12,А13,А14,А15,А16,А17)"
    },
    {
        "name": "Менаџмент технологије и развоја",
        "lecture_session_time": "Понедељак - 12:15-14:00 Амфитеатар 4 (А1,А2,А3,А4,А5,А6,А7,А8,А9,А10)"
    },
    {
        "name": "Инжењеринг процеса",
        "lecture_session_time": "Понедељак - 12:15-14:00 Амфитеатар 5 (А1,А2,А3)"
    },
    {
        "name": "Социологија",
        "lecture_session_time": "Понедељак - 14:15-16:00 Амфитеатар 1 (А11,А12,А13,А14,А15,А16,А17)"
    },
    {
        "name": "Социологија",
        "lecture_session_time": "Понедељак - 14:15-16:00 Амфитеатар 1 (А1,А2,А3,А4,А5,А6,А7,А8,А9,А10)"
    },
    {
        "name": "Енглески језик у менаџменту 1",
        "lecture_session_time": "Понедељак - 16:15-18:00 Амфитеатар 1 (А14,А15,А16,А17)"
    },
    {
        "name": "Психологија",
        "lecture_session_time": "Уторак - 08:15-10:00 Амфитеатар 1 (А1,А2,А3,А7,А8,А9,А10)"
    },
    {
        "name": "Математика 2",
        "lecture_session_time": "Уторак - 08:15-10:00 Амфитеатар 2 (А11,А12,А13)"
    },
    {
        "name": "Математика 2",
        "exercise_session_time": "Уторак - 08:15-10:00 16 (А16)"
    },
    {
        "name": "Математика 2",
        "exercise_session_time": "Уторак - 08:15-10:00 14 (А4)"
    },
    {
        "name": "Социологија",
        "exercise_session_time": "Уторак - 10:15-12:00 20 (А16)"
    },
    {
        "name": "Принципи програмирања",
        "exercise_session_time": "Уторак - 10:15-12:00 40 (А3)"
    },
    {
        "name": "Увод у информационе системе",
        "lecture_session_time": "Уторак - 10:15-12:00 Амфитеатар 2 (А11,А12,А13)"
    },
    {
        "name": "Психологија",
        "exercise_session_time": "Уторак - 10:15-12:00 18 (А14)"
    },
    {
        "name": "Математика 2",
        "exercise_session_time": "Уторак - 10:15-12:00 15 (А2)"
    },
    {
        "name": "Принципи програмирања",
        "exercise_session_time": "Уторак - 10:15-12:00 50 (А3)"
    },
    {
        "name": "Математика 2",
        "lecture_session_time": "Уторак - 10:15-12:00 Амфитеатар 1 (А7,А8,А9,А10)"
    },
    {
        "name": "Енглески језик у менаџменту 1",
        "exercise_session_time": "Уторак - 10:15-12:00 17 (А15)"
    },
    {
        "name": "Увод у информационе системе",
        "exercise_session_time": "Уторак - 10:15-12:00 62 (А4)"
    },
    {
        "name": "Математика 2",
        "exercise_session_time": "Уторак - 10:15-12:00 14 (А1)"
    },
    {
        "name": "Менаџмент технологије и развоја",
        "exercise_session_time": "Уторак - 12:15-14:00 Читаоница (А7,А8,А9,А10)"
    },
    {
        "name": "Психологија",
        "exercise_session_time": "Уторак - 12:15-14:00 Амфитеатар 5 (А1,А15)"
    },
    {
        "name": "Инжењеринг процеса",
        "lecture_session_time": "Уторак - 12:15-14:00 Амфитеатар 1 (А7,А8,А9,А10)"
    },
    {
        "name": "Принципи програмирања",
        "exercise_session_time": "Уторак - 12:15-14:00 50 (А5)"
    },
    {
        "name": "Принципи програмирања",
        "exercise_session_time": "Уторак - 12:15-14:00 40 (А5)"
    },
    {
        "name": "Социологија",
        "exercise_session_time": "Уторак - 12:15-14:00 18 (А14)"
    },
    {
        "name": "Увод у информационе системе",
        "exercise_session_time": "Уторак - 12:15-14:00 62 (А6)"
    },
    {
        "name": "Енглески језик у менаџменту 1",
        "lecture_session_time": "Уторак - 12:15-14:00 Амфитеатар 2 (А11,А12,А13)"
    },
    {
        "name": "Енглески језик у менаџменту 1",
        "exercise_session_time": "Уторак - 12:15-14:00 20 (А16)"
    },
    {
        "name": "Социологија",
        "exercise_session_time": "Уторак - 14:15-16:00 17 (А15)"
    },
    {
        "name": "Принципи програмирања",
        "exercise_session_time": "Уторак - 14:15-16:00 40 (А6)"
    },
    {
        "name": "Увод у информационе системе",
        "exercise_session_time": "Уторак - 14:15-16:00 62 (А5)"
    },
    {
        "name": "Енглески језик у менаџменту 1",
        "exercise_session_time": "Уторак - 14:15-16:00 18 (А14)"
    },
    {
        "name": "Француски језик у менаџменту 1",
        "lecture_session_time": "Уторак - 14:15-16:00 16 (А11,А12,А13,А14,А15,А16,А17)"
    },
    {
        "name": "Принципи програмирања",
        "exercise_session_time": "Уторак - 14:15-16:00 50 (А6)"
    },
    {
        "name": "Социологија",
        "exercise_session_time": "Уторак - 16:15-18:00 17 (А1,А2,А3,А4,А5,А6,А7,А8,А9,А10)"
    },
    {
        "name": "Француски језик у менаџменту 1",
        "exercise_session_time": "Уторак - 16:15-18:00 16 (А11,А12,А13,А14,А15,А16,А17)"
    },
    {
        "name": "Психологија",
        "exercise_session_time": "Среда - 08:15-10:00 14 (А11)"
    },
    {
        "name": "Математика 2",
        "lecture_session_time": "Среда - 08:15-10:00 Амфитеатар 1 (А14,А15,А16,А17)"
    },
    {
        "name": "Увод у информационе системе",
        "lecture_session_time": "Среда - 08:15-10:00 Амфитеатар 3 (А1,А2,А3)"
    },
    {
        "name": "Принципи програмирања",
        "exercise_session_time": "Среда - 08:15-10:00 50 (А10)"
    },
    {
        "name": "Принципи програмирања",
        "exercise_session_time": "Среда - 08:15-10:00 40 (А10)"
    },
    {
        "name": "Увод у информационе системе",
        "exercise_session_time": "Среда - 08:15-10:00 62 (А12)"
    },
    {
        "name": "Математика 2",
        "exercise_session_time": "Среда - 10:15-12:00 13 (А12)"
    },
    {
        "name": "Принципи програмирања",
        "exercise_session_time": "Среда - 10:15-12:00 50 (А2)"
    },
    {
        "name": "Принципи програмирања",
        "exercise_session_time": "Среда - 10:15-12:00 40 (А2)"
    },
    {
        "name": "Психологија",
        "exercise_session_time": "Среда - 10:15-12:00 18 (А3)"
    },
    {
        "name": "Менаџмент технологије и развоја",
        "exercise_session_time": "Среда - 10:15-12:00 16 (А4,А5,А6)"
    },
    {
        "name": "Социологија",
        "exercise_session_time": "Среда - 10:15-12:00 14 (А11)"
    },
    {
        "name": "Увод у информационе системе",
        "lecture_session_time": "Среда - 10:15-12:00 Амфитеатар 1 (А14,А15,А16,А17)"
    },
    {
        "name": "Инжењеринг процеса",
        "lecture_session_time": "Среда - 10:15-12:00 Амфитеатар 2 (А4,А5,А6)"
    },
    {
        "name": "Инжењеринг процеса",
        "exercise_session_time": "Среда - 10:15-12:00 15 (А10)"
    },
    {
        "name": "Увод у информационе системе",
        "exercise_session_time": "Среда - 10:15-12:00 62 (А1)"
    },
    {
        "name": "Социологија",
        "exercise_session_time": "Среда - 12:15-14:00 13 (А12)"
    },
    {
        "name": "Математика 2",
        "exercise_session_time": "Среда - 12:15-14:00 15 (А10)"
    },
    {
        "name": "Увод у информационе системе",
        "exercise_session_time": "Среда - 12:15-14:00 62 (А13)"
    },
    {
        "name": "Менаџмент технологије и развоја",
        "exercise_session_time": "Среда - 12:15-14:00 16 (А1,А2,А3)"
    },
    {
        "name": "Математика 2",
        "exercise_session_time": "Среда - 12:15-14:00 17 (А8)"
    },
    {
        "name": "Принципи програмирања",
        "lecture_session_time": "Среда - 12:15-14:00 Амфитеатар 2 (А4,А5,А6)"
    },
    {
        "name": "Психологија",
        "lecture_session_time": "Среда - 14:15-16:00 Амфитеатар 2 (А4,А5,А6)"
    },
    {
        "name": "Увод у информационе системе",
        "exercise_session_time": "Среда - 14:15-16:00 62 (А7)"
    },
    {
        "name": "Математика 2",
        "exercise_session_time": "Среда - 14:15-16:00 15 (А13)"
    },
    {
        "name": "Психологија",
        "exercise_session_time": "Среда - 14:15-16:00 17 (А8)"
    },
    {
        "name": "Увод у информационе системе",
        "exercise_session_time": "Среда - 16:15-18:00 62 (А8)"
    },
    {
        "name": "Психологија",
        "exercise_session_time": "Среда - 16:15-18:00 17 (А7)"
    },
    {
        "name": "Енглески језик у менаџменту 1",
        "exercise_session_time": "Четвртак - 08:15-10:00 17 (А11)"
    },
    {
        "name": "Увод у информационе системе",
        "exercise_session_time": "Четвртак - 08:15-10:00 62 (А14)"
    },
    {
        "name": "Психологија",
        "exercise_session_time": "Четвртак - 08:15-10:00 16 (А13)"
    },
    {
        "name": "Принципи програмирања",
        "exercise_session_time": "Четвртак - 08:15-10:00 40 (А7)"
    },
    {
        "name": "Принципи програмирања",
        "exercise_session_time": "Четвртак - 08:15-10:00 50 (А7)"
    },
    {
        "name": "Инжењеринг процеса",
        "exercise_session_time": "Четвртак - 08:15-10:00 20 (А4)"
    },
    {
        "name": "Математика 2",
        "exercise_session_time": "Четвртак - 08:15-10:00 13 (А17)"
    },
    {
        "name": "Математика 2",
        "exercise_session_time": "Четвртак - 10:15-12:00 14 (А14)"
    },
    {
        "name": "Принципи програмирања",
        "exercise_session_time": "Четвртак - 10:15-12:00 40 (А4)"
    },
    {
        "name": "Психологија",
        "exercise_session_time": "Четвртак - 10:15-12:00 13 (А17)"
    },
    {
        "name": "Инжењеринг процеса",
        "exercise_session_time": "Четвртак - 10:15-12:00 21 (А1)"
    },
    {
        "name": "Увод у информационе системе",
        "exercise_session_time": "Четвртак - 10:15-12:00 62 (А11)"
    },
    {
        "name": "Математика 2",
        "exercise_session_time": "Четвртак - 10:15-12:00 17 (А7)"
    },
    {
        "name": "Принципи програмирања",
        "exercise_session_time": "Четвртак - 10:15-12:00 50 (А4)"
    },
    {
        "name": "Социологија",
        "exercise_session_time": "Четвртак - 10:15-12:00 16 (А13)"
    },
    {
        "name": "Социологија",
        "exercise_session_time": "Четвртак - 12:15-14:00 13 (А17)"
    },
    {
        "name": "Математика 2",
        "exercise_session_time": "Четвртак - 12:15-14:00 14 (А11)"
    },
    {
        "name": "Инжењеринг процеса",
        "exercise_session_time": "Четвртак - 12:15-14:00 17 (А7)"
    },
    {
        "name": "Енглески језик у менаџменту 1",
        "exercise_session_time": "Четвртак - 12:15-14:00 16 (А13)"
    },
    {
        "name": "Увод у информационе системе",
        "exercise_session_time": "Четвртак - 12:15-14:00 62 (А9)"
    },
    {
        "name": "Математика 2",
        "exercise_session_time": "Четвртак - 12:15-14:00 12 (А3)"
    },
    {
        "name": "Психологија",
        "exercise_session_time": "Четвртак - 12:15-14:00 15 (А4)"
    },
    {
        "name": "Принципи програмирања",
        "exercise_session_time": "Четвртак - 12:15-14:00 40 (А1)"
    },
    {
        "name": "Принципи програмирања",
        "exercise_session_time": "Четвртак - 12:15-14:00 50 (А1)"
    },
    {
        "name": "Инжењеринг процеса",
        "exercise_session_time": "Четвртак - 14:15-16:00 21 (А2)"
    },
    {
        "name": "Увод у информационе системе",
        "exercise_session_time": "Четвртак - 14:15-16:00 62 (А3)"
    },
    {
        "name": "Енглески језик у менаџменту 1",
        "exercise_session_time": "Четвртак - 14:15-16:00 12 (А12)"
    },
    {
        "name": "Психологија",
        "exercise_session_time": "Четвртак - 14:15-16:00 17 (А9)"
    },
    {
        "name": "Инжењеринг процеса",
        "exercise_session_time": "Четвртак - 16:15-18:00 21 (А3)"
    },
    {
        "name": "Психологија",
        "exercise_session_time": "Четвртак - 16:15-18:00 12 (А12)"
    },
    {
        "name": "Психологија",
        "exercise_session_time": "Петак - 08:15-10:00 17 (А16)"
    },
    {
        "name": "Математика 2",
        "exercise_session_time": "Петак - 08:15-10:00 16 (А15)"
    },
    {
        "name": "Основе операционог менаџмента",
        "exercise_session_time": "Петак - 08:15-10:00 14 (А1,А2,А3,А4,А5,А6,А7,А8,А9,А10)"
    },
    {
        "name": "Увод у информационе системе",
        "exercise_session_time": "Петак - 08:15-10:00 62 (А17)"
    },
    {
        "name": "Инжењеринг процеса",
        "exercise_session_time": "Петак - 08:15-10:00 13 (А6)"
    },
    {
        "name": "Програмирање 1",
        "exercise_session_time": "Петак - 10:15-12:00 07 (А-акр2014)"
    },
    {
        "name": "Енглески језик у менаџменту 1",
        "exercise_session_time": "Петак - 10:15-12:00 12 (А17)"
    },
    {
        "name": "Увод у информационе системе",
        "exercise_session_time": "Петак - 10:15-12:00 62 (А16)"
    },
    {
        "name": "Психологија",
        "exercise_session_time": "Петак - 10:15-12:00 21 (А5)"
    },
    {
        "name": "Математика 2",
        "exercise_session_time": "Петак - 10:15-12:00 13 (А6)"
    },
    {
        "name": "Програмирање 1",
        "exercise_session_time": "Петак - 10:15-12:00 06 (А-акр2014)"
    },
    {
        "name": "Инжењеринг процеса",
        "exercise_session_time": "Петак - 10:15-12:00 17 (А8)"
    },
    {
        "name": "Математика 2",
        "exercise_session_time": "Петак - 10:15-12:00 16 (А9)"
    },
    {
        "name": "Увод у информационе системе",
        "exercise_session_time": "Петак - 12:15-14:00 62 (А15)"
    },
    {
        "name": "Инжењеринг процеса",
        "exercise_session_time": "Петак - 12:15-14:00 16 (А9)"
    },
    {
        "name": "Принципи програмирања",
        "exercise_session_time": "Петак - 12:15-14:00 50 (А8)"
    },
    {
        "name": "Математика 2",
        "exercise_session_time": "Петак - 12:15-14:00 21 (А5)"
    },
    {
        "name": "Психологија",
        "exercise_session_time": "Петак - 12:15-14:00 13 (А6)"
    },
    {
        "name": "Принципи програмирања",
        "exercise_session_time": "Петак - 12:15-14:00 40 (А8)"
    },
    {
        "name": "Увод у информационе системе",
        "exercise_session_time": "Петак - 14:15-16:00 62 (А2)"
    },
    {
        "name": "Инжењеринг процеса",
        "exercise_session_time": "Петак - 14:15-16:00 21 (А5)"
    },
    {
        "name": "Психологија",
        "exercise_session_time": "Петак - 14:15-16:00 13 (А10)"
    },
    {
        "name": "Принципи програмирања",
        "exercise_session_time": "Петак - 14:15-16:00 50 (А9)"
    },
    {
        "name": "Принципи програмирања",
        "exercise_session_time": "Петак - 14:15-16:00 40 (А9)"
    },
    {
        "name": "Увод у информационе системе",
        "exercise_session_time": "Петак - 16:15-18:00 62 (А10)"
    },
    {
        "name": "Психологија",
        "exercise_session_time": "Петак - 16:15-18:00 13 (А2)"
    }
]